comportlist-0.1.1.dist-info/METADATA
comportlist-0.1.1.dist-info/WHEEL
comportlist/__init__.py
comportlist/comportlist.cp38-win_amd64.pyd
comportlist-0.1.1.dist-info/RECORD
